freqsap/__init__.py
freqsap/__main__.py
freqsap/accession.py
freqsap/allele.py
freqsap/dbsnp.py
freqsap/ebi.py
freqsap/exceptions.py
freqsap/interfaces.py
freqsap/protein.py
freqsap/report.py
freqsap/study.py
freqsap/uniprot.py
freqsap/variation.py
freqsap-1.1.0.dist-info/licenses/LICENSE
freqsap-1.1.0.dist-info/METADATA
freqsap-1.1.0.dist-info/WHEEL
freqsap-1.1.0.dist-info/entry_points.txt
freqsap-1.1.0.dist-info/top_level.txt
freqsap-1.1.0.dist-info/RECORD
