Metadata-Version: 2.4
Name: freqsap
Version: 1.1.0
Summary: freqsap can be used to query the frequency of single amino-acid polymorphisms
Author-email: Helge Hecht <helge.hecht@recetox.muni.cz>
License: MIT License
Project-URL: Repository, https://github.com/RECETOX/freqsap
Project-URL: Issues, https://github.com/RECETOX/freqsap/issues
Project-URL: Changelog, https://github.com/RECETOX/freqsap/CHANGELOG.md
Project-URL: ReadTheDocs, https://freqsap.readthedocs.io
Keywords: proteomics,dbsnp,amino-acid,polymorphism
Classifier: Development Status :: 2 - Pre-Alpha
Classifier: Intended Audience :: Developers
Classifier: Intended Audience :: Science/Research
Classifier: Natural Language :: English
Classifier: Programming Language :: Python :: 3
Classifier: Programming Language :: Python :: 3.10
Classifier: Programming Language :: Python :: 3.11
Classifier: Programming Language :: Python :: 3.12
Requires-Python: >=3.8
License-File: LICENSE
Requires-Dist: requests
Requires-Dist: openpyxl
Provides-Extra: dev
Requires-Dist: build; extra == "dev"
Requires-Dist: bump-my-version; extra == "dev"
Requires-Dist: coverage[toml]; extra == "dev"
Requires-Dist: pytest; extra == "dev"
Requires-Dist: pytest-cov; extra == "dev"
Requires-Dist: ruff; extra == "dev"
Requires-Dist: sphinx; extra == "dev"
Requires-Dist: sphinx_rtd_theme; extra == "dev"
Requires-Dist: sphinx-autoapi; extra == "dev"
Requires-Dist: tox; extra == "dev"
Requires-Dist: myst_parser; extra == "dev"
Provides-Extra: docs
Requires-Dist: sphinx; extra == "docs"
Requires-Dist: sphinx_rtd_theme; extra == "docs"
Requires-Dist: sphinx-autoapi; extra == "docs"
Requires-Dist: myst_parser; extra == "docs"
Provides-Extra: publishing
Requires-Dist: build; extra == "publishing"
Requires-Dist: twine; extra == "publishing"
Requires-Dist: wheel; extra == "publishing"
Dynamic: license-file
